nlp_model_gen/__init__.py
nlp_model_gen/base.py
nlp_model_gen/paths.json
nlp_model_gen/__pycache__/__init__.cpython-36.pyc
nlp_model_gen/__pycache__/base.cpython-36.pyc
nlp_model_gen/config/resources/configurationTemplates.json
nlp_model_gen/config/resources/file_load.py
nlp_model_gen/config/resources/test_file_a.txt
nlp_model_gen/config/resources/test_file_b.txt
nlp_model_gen/config/resources/test_file_c.txt
nlp_model_gen/config/resources/train_data_test.py
nlp_model_gen/config/resources/wordProcessorInitialDefault.json
nlp_model_gen/config/testScripts/testDataGenerator.py
nlp_model_gen/constants/constants.py
nlp_model_gen/constants/__pycache__/constants.cpython-36.pyc
nlp_model_gen/packages/adminModule/AdminModuleController.py
nlp_model_gen/packages/adminModule/__pycache__/AdminModuleController.cpython-36.pyc
nlp_model_gen/packages/adminModule/analyzerRulesGenerator/AnalyzerRulesGenerator.py
nlp_model_gen/packages/adminModule/analyzerRulesGenerator/__pycache__/AnalyzerRulesGenerator.cpython-36.pyc
nlp_model_gen/packages/adminModule/packageUtils/token_tags.py
nlp_model_gen/packages/adminModule/packageUtils/validations.py
nlp_model_gen/packages/adminModule/packageUtils/__pycache__/token_tags.cpython-36.pyc
nlp_model_gen/packages/adminModule/packageUtils/__pycache__/validations.cpython-36.pyc
nlp_model_gen/packages/adminModule/tokenGenerator/TokenGenerator.py
nlp_model_gen/packages/adminModule/tokenGenerator/__pycache__/TokenGenerator.cpython-36.pyc
nlp_model_gen/packages/adminModule/tokenizerRulesGenerator/TokenizerRulesGenerator.py
nlp_model_gen/packages/adminModule/tokenizerRulesGenerator/__pycache__/TokenizerRulesGenerator.cpython-36.pyc
nlp_model_gen/packages/applicationModule/ApplicationModuleController.py
nlp_model_gen/packages/applicationModule/__pycache__/ApplicationModuleController.cpython-36.pyc
nlp_model_gen/packages/applicationModule/dataSanitizer/DataSanitizer.py
nlp_model_gen-0.2.1.dist-info/DESCRIPTION.rst
nlp_model_gen-0.2.1.dist-info/METADATA
nlp_model_gen-0.2.1.dist-info/RECORD
nlp_model_gen-0.2.1.dist-info/WHEEL
nlp_model_gen-0.2.1.dist-info/metadata.json
nlp_model_gen-0.2.1.dist-info/top_level.txt
