Metadata-Version: 2.0
Name: nlp-model-gen
Version: 0.2.1
Summary: A spaCy model customizer and management tool
Home-page: https://github.com/galias11/nlp_model_gen
Author: Gerardo Alias
Author-email: alias_gerardo@yahoo.com.ar
License: UNKNOWN
Platform: UNKNOWN
Classifier: Programming Language :: Python :: 3
Classifier: License :: OSI Approved :: MIT License
Classifier: Operating System :: OS Independent
Requires-Dist: spacy (==2.0.18)
Requires-Dist: pymongo (>=3.7.2)
Requires-Dist: schema (>=0.6.8)
Requires-Dist: termcolor (>=1.1.0)
Requires-Dist: terminaltables (>=3.1.0)
Requires-Dist: gitpython (>=2.1.11)
